example/__init__.py
example/app.py
example/app_2.py
skywalking_sanic/__init__.py
skywalking_sanic-0.0.6.dist-info/LICENSE
skywalking_sanic-0.0.6.dist-info/METADATA
skywalking_sanic-0.0.6.dist-info/WHEEL
skywalking_sanic-0.0.6.dist-info/top_level.txt
skywalking_sanic-0.0.6.dist-info/RECORD
